tap_userflow/__init__.py
tap_userflow/client.py
tap_userflow/schemas/content-session.json
tap_userflow/schemas/content.json
tap_userflow/streams.py
tap_userflow/tap.py
tap_userflow/tests/__init__.py
tap_userflow/tests/test_core.py
tap_userflow-0.0.3.dist-info/entry_points.txt
tap_userflow-0.0.3.dist-info/WHEEL
tap_userflow-0.0.3.dist-info/METADATA
tap_userflow-0.0.3.dist-info/RECORD
