Metadata-Version: 2.1
Name: tap-userflow
Version: 0.0.3
Summary: `tap-userflow` is a Singer tap for UserFlow, built with the Meltano SDK for Singer Taps.
License: Apache 2.0
Keywords: ELT,UserFlow
Author: Ilkka Peltola
Requires-Python: >=3.7.1,<3.11
Classifier: License :: Other/Proprietary License
Classifier: Programming Language :: Python :: 3
Classifier: Programming Language :: Python :: 3.10
Classifier: Programming Language :: Python :: 3.8
Classifier: Programming Language :: Python :: 3.9
Requires-Dist: requests (>=2.25.1,<3.0.0)
Requires-Dist: singer-sdk (>=0.5.0,<0.6.0)
